song/__init__.py
song/cli.py
song_runner-0.1.3.dist-info/METADATA
song_runner-0.1.3.dist-info/WHEEL
song_runner-0.1.3.dist-info/entry_points.txt
song_runner-0.1.3.dist-info/top_level.txt
song_runner-0.1.3.dist-info/RECORD
