Metadata-Version: 2.4
Name: song-runner
Version: 0.1.3
Summary: A YouTube song runner CLI
Author: Vishesh Jain
Author-email: Vishesh Jain <visheshj2005@example.com>
Classifier: Programming Language :: Python :: 3
Classifier: License :: OSI Approved :: MIT License
Classifier: Operating System :: OS Independent
Requires-Python: >=3.7
Requires-Dist: yt-dlp
Requires-Dist: ffpyplayer
Requires-Dist: youtube-search-python
Dynamic: author
Dynamic: description-content-type
Dynamic: requires-python
